CHANGELOG.md
dramatiq_mongodb/__init__.py
dramatiq_mongodb/backend.py
dramatiq_mongodb/broker.py
dramatiq_mongodb/state.py
dramatiq_mongodb-0.8.3.dist-info/LICENSE
dramatiq_mongodb-0.8.3.dist-info/METADATA
dramatiq_mongodb-0.8.3.dist-info/WHEEL
dramatiq_mongodb-0.8.3.dist-info/RECORD
