Metadata-Version: 2.1
Name: dramatiq-mongodb
Version: 0.8.3
Summary: Dramatiq-Mongodb Broker and Results Backend for Dramatiq
Home-page: https://github.com/obscuritylabs/dramatiq-mongodb
License: MIT
Author: Tory Clasen
Author-email: ToryClasen@Gmail.com
Requires-Python: >=3.7,<4
Classifier: License :: OSI Approved :: MIT License
Classifier: Programming Language :: Python :: 3
Classifier: Programming Language :: Python :: 3.7
Classifier: Programming Language :: Python :: 3.8
Classifier: Programming Language :: Python :: 3.9
Classifier: Programming Language :: Python :: 3.10
Classifier: Programming Language :: Python :: 3.11
Requires-Dist: dramatiq (>=1.14.2,<2.0.0)
Requires-Dist: pymongo (>=4.1,<5)
Project-URL: Repository, https://github.com/obscuritylabs/dramatiq-mongodb
